Workbook
Name Slicer_Category: #N/A
Name Slicer_Customer_Segment: #N/A
Name Slicer_Order_Status: #N/A
Name Slicer_Region: #N/A
Name Slicer_Years__Shipping_Date: #N/A

Sheet Dashboard

Sheet Report
E1: E-COMMERCE SALES DASHBOARD REPORT
D3: 1. Sales Performance
D4: The business generated total sales of ₹10.79Cr from 963 orders and sold 3,420 units during the selected periods.
D5: 2.Category Sales
D6: Electronics Contributed the Highest Share of total sales among all Category.
D7: 3.Sales Channel
D8: Online Sales Channel Generated The Majority Of Sales Revenue.
D9: 4.Region Comparison
D10: South Region recorded the highest sales while Central Region Generated the Lowest Sales.
D11: 5.Top 5 Brands
D12: Apple,Samsung,Sony,Dell, LG Were the top revenue-generating brands.
D13: 6.Payment method
D14: Cusomer Preferred Digital Payment method over Traditional Payment methods.
... D16: July Recorded the Highest Sales,While September showed the Lowest Sales.

Sheet KPIs
A2: Total Sales | B2: Sum of Discount_Amt | C2: Original Sales | D2: Count of Order_ID | E2: Sum of Quantity
A3: 1.0362632e+08 | B3: 7731562.5 | C3: 1.0796228e+08 | D3: 1000 | E3: 3420 | G3: Total count
G4: =COUNTA(_xlfn.UNIQUE(Sales_Transactions_Raw[Order_ID])) -> 963

Sheet Month wise sales
A3: Row Labels | B3: Sum of Sales | D3: Row Labels | E3: Sum of Sales
A4: 2023 | B4: 69190780 | D4: Jan | E4: 10298993
A5: 2024 | B5: 34435541 | D5: Feb | E5: 11143709
A6: Grand Total | B6: 1.0362632e+08 | D6: Mar | E6: 11291454
D7: Apr | E7: 11107004
D8: May | E8: 9255504.2
D9: Jun | E9: 10515882
D10: Jul | E10: 6847649.2
D11: Aug | E11: 5898620
D12: Sep | E12: 7374140
D13: Oct | E13: 7807125.7
D14: Nov | E14: 5590691.1
D15: Dec | E15: 6495549.2
D16: Grand Total | E16: 1.0362632e+08

Sheet Category sales
A3: Row Labels | B3: Sum of Sales | D3: Row Labels | E3: Sum of Sales
A4: Mobile App | B4: 23551653 | D4: Appliances | E4: 18429353
A5: Online | B5: 24213525 | D5: Electronics | E5: 70886288
A6: Partner | B6: 21622199 | D6: Fashion | E6: 5458683.9
A7: Phone | B7: 19122325 | D7: Furniture | E7: 8225687.7
A8: Store | B8: 15116618 | D8: Grocery | E8: 412804.16
A9: Grand Total | B9: 1.0362632e+08 | D9: Stationery | E9: 213503.54
D10: Grand Total | E10: 1.0362632e+08

Sheet Saleschan(Sales)
A3: Row Labels | B3: Sum of Sales
A4: Mobile App | B4: 23551653
A5: Online | B5: 24213525
A6: Partner | B6: 21622199
A7: Phone | B7: 19122325
A8: Store | B8: 15116618
A9: Grand Total | B9: 1.0362632e+08

Sheet Payment method
A3: Row Labels | B3: Count of Customer_Name
A4: Cash On Delivery | B4: 122
A5: Credit Card | B5: 147
A6: Debit Card | B6: 156
A7: Emi | B7: 140
A8: Net Banking | B8: 151
A9: Upi | B9: 151
A10: Wallet | B10: 133
A11: Grand Total | B11: 1000

Sheet Regionwise
A3: Row Labels | B3: Sum of new total amt | C3: Sum of Sales | E3: Row Labels | F3: Sum of Sales
A4: Central | B4: 6887696 | C4: 6701564 | E4: Apple | F4: 15368920
A5: East | B5: 22416406 | C5: 21118018 | E5: Dell | F5: 9587010
A6: North | B6: 23429364 | C6: 22514737 | E6: Lg | F6: 6565227.1
A7: South | B7: 35153104 | C7: 33997514 | E7: Samsung | F7: 15270569
A8: West | B8: 20075707 | C8: 19294488 | E8: Sony | F8: 6634987.8
A9: Grand Total | B9: 1.0796228e+08 | C9: 1.0362632e+08 | E9: Grand Total | F9: 53426714

Sheet Sales_Transactions_Raw
A1: Order_ID | B1: Customer_Name | C1: Customer_Segment | D1: Product_Name | E1: Brand | F1: Category | G1: Sub_Category | H1: Unit_Price | I1: Sales | J1: Quantity | K1: Discount_Pct | L1: Discount_Amt | M1: Subtotal | N1: Tax_Pct | O1: Tax_Amt | P1: Shipping_Charge | Q1: new total amt | R1: Payment_Method | S1: Shipping_Method | T1: Order_Status | U1: Sales_Channel | V1: Sales_Rep | W1: Sales_Rep_Region | X1: City | Y1: State | Z1: Region | AA1: Pincode | AB1: Coupon_Code | AC1: Customer_Rating | AD1: Return_Flag | AE1: Return_Reason | AF1: Warehouse_ID | AG1: Delivery_Partner | AH1: Order Date | AI1: Shipping Date | AJ1: Delivery Date | AK1: Email | AL1: Mobile no
A2: ORD-2023006 | B2: Zubair Khan | C2: Retail | D2: Hp Laserjet 1020 | E2: Hp | F2: Electronics | G2: Printers | H2: 11670 | I2: =Sales_Transactions_Raw[[#This Row],[Unit_Price]]*Sales_Transactions_Raw[[#This Row],[Quantity]] -> 81690 | J2: 7 | K2: 5 | L2: 4084.5 | M2: 77605.5 | N2: 18 | O2: 13968.99 | P2: 0 | Q2: 91574.49 | R2: Debit Card | S2: Express | T2: Delivered | U2: Partner | V2: Suraj Verma | W2: East | X2: Udaipur | Y2: Rajasthan | Z2: North | AA2: 489202 | AB2: None | AC2: 4 | AD2: No | AE2: other | AF2: WH-12 | AG2: Delhivery | AH2: 45069 | AI2: 45075 | AJ2: 45078 | AK2: zubair_khan@gmail_com | AL2: 9654235116
A3: ORD-2023198 | B3: Archana Srivastava | C3: Retail | D3: Hp Pavilion 15 | E3: Hp | F3: Electronics | G3: Laptops | H3: 58650 | I3: =Sales_Transactions_Raw[[#This Row],[Unit_Price]]*Sales_Transactions_Raw[[#This Row],[Quantity]] -> 351900 | J3: 6 | K3: 5 | L3: 17595 | M3: 334305 | N3: 18 | O3: 60174.9 | P3: 0 | Q3: 394479.9 | R3: Emi | S3: Standard | T3: Shipped | U3: Partner | V3: Vinay Joshi | W3: Central | X3: Jodhpur | Y3: Rajasthan | Z3: North | AA3: 489581 | AB3: None | AC3: 4 | AD3: No | AE3: other | AF3: WH-03 | AG3: Dtdc | AH3: 45030 | AI3: 45034 | AJ3: 45040 | AK3: srivastava_archana@gmail_com | AL3: 7030564139
A4: ORD-2023014 | B4: Mohan Tiwari | C4: Retail | D4: Sony Bravia 55-Inch | E4: Sony | F4: Electronics | G4: Televisions | H4: 78600 | I4: =Sales_Transactions_Raw[[#This Row],[Unit_Price]]*Sales_Transactions_Raw[[#This Row],[Quantity]] -> 235800 | J4: 3 | K4: 0 | L4: 0 | M4: 235800 | N4: 18 | O4: 42444 | P4: 0 | Q4: 278244 | R4: Credit Card | S4: Standard | T4: Shipped | U4: Partner | V4: Priya Sinha | W4: West | X4: Ranchi | Y4: Jharkhand | Z4: East | AA4: 182575 | AB4: Newuser | AC4: 4 | AD4: No | AE4: other | AF4: WH-09 | AG4: Ekart | AH4: 45359 | AI4: 45364 | AJ4: 45040 | AK4: mtiwari@gmail_com | AL4: 9814893252
A5: ORD-2023124 | B5: Venkatesan Rajan | C5: Wholesale | D5: Samsung 65-Inch Qled | E5: Samsung | F5: Electronics | G5: Televisions | H5: 98240 | I5: =Sales_Transactions_Raw[[#This Row],[Unit_Price]]*Sales_Transactions_Raw[[#This Row],[Quantity]] -> 392960 | J5: 4 | K5: 5 | L5: 19648 | M5: 373312 | N5: 18 | O5: 67196.16 | P5: 0 | Q5: 440508.16 | R5: Upi | S5: Economy | T5: Shipped | U5: Partner | V5: Deepa Menon | W5: South | X5: Bengaluru | Y5: Karnataka | Z5: South | AA5: 166803 | AB5: None | AC5: 4 | AD5: No | AE5: other | AF5: WH-11 | AG5: Delhivery | AH5: 45360 | AI5: 45362 | AJ5: 45372 | AK5: venkatesan_rajan@gmail_com | AL5: 8310518347
A6: ORD-2023090 | B6: Anita Bhatt | C6: Wholesale | D6: Nikon D3500 | E6: Nikon | F6: Electronics | G6: Cameras | H6: 37090 | I6: =Sales_Transactions_Raw[[#This Row],[Unit_Price]]*Sales_Transactions_Raw[[#This Row],[Quantity]] -> 74180 | J6: 2 | K6: 0 | L6: 0 | M6: 74180 | N6: 18 | O6: 13352.4 | P6: 0 | Q6: 87532.4 | R6: Wallet | S6: Overnight | T6: Processing | U6: Online | V6: Suraj Verma | W6: East | X6: Chandigarh | Y6: Punjab | Z6: North | AA6: 162579 | AB6: Save10 | AC6: 4 | AD6: No | AE6: other | AF6: WH-09 | AG6: Amazon Logistics | AH6: 45386 | AI6: 45388 | AJ6: 45396 | AK6: anita_bhatt@outlook_com | AL6: 6602606474
A7: ORD-2023019 | B7: Paramjit Brar | C7: Retail | D7: Hp Pavilion 15 | E7: Hp | F7: Electronics | G7: Laptops | H7: 62690 | I7: =Sales_Transactions_Raw[[#This Row],[Unit_Price]]*Sales_Transactions_Raw[[#This Row],[Quantity]] -> 564210 | J7: 9 | K7: 10 | L7: 56421 | M7: 507789 | N7: 18 | O7: 91402.02 | P7: 0 | Q7: 599191.02 | R7: Credit Card | S7: Economy | T7: Delivered | U7: Partner | V7: Raj Kumar | W7: North | X7: Kanpur | Y7: Uttar Pradesh | Z7: North | AA7: 691543 | AB7: None | AC7: 4 | AD7: No | AE7: other | AF7: WH-11 | AG7: Delhivery | AH7: 44996 | AI7: 45002 | AJ7: 45007 | AK7: pbrar@gmail_com | AL7: 7079911838
A8: ORD-2023073 | B8: Mohan Tiwari | C8: Retail | D8: Lenovo Thinkpad E14 | E8: Lenovo | F8: Electronics | G8: Laptops | H8: 55250 | I8: =Sales_Transactions_Raw[[#This Row],[Unit_Price]]*Sales_Transactions_Raw[[#This Row],[Quantity]] -> 221000 | J8: 4 | K8: 10 | L8: 22100 | M8: 198900 | N8: 18 | O8: 35802 | P8: 0 | Q8: 234702 | R8: Net Banking | S8: Same Day | T8: Delivered | U8: Online | V8: Deepa Menon | W8: South | X8: Indore | Y8: Madhya Pradesh | Z8: Central | AA8: 536118 | AB8: Festive20 | AC8: 4 | AD8: No | AE8: other | AF8: WH-12 | AG8: Delhivery | AH8: 45086 | AI8: 45089 | AJ8: 45095 | AK8: mohant@gmail_com | AL8: 8680112805
A9: ORD-2023048 | B9: Vishal Chaudhary | C9: VIP | D9: Bajaj Mixer 750W | E9: Bajaj | F9: Appliances | G9: Kitchen | H9: 2940 | I9: =Sales_Transactions_Raw[[#This Row],[Unit_Price]]*Sales_Transactions_Raw[[#This Row],[Quantity]] -> 17640 | J9: 6 | K9: 0 | L9: 0 | M9: 17640 | N9: 5 | O9: 882 | P9: 0 | Q9: 18522 | R9: Credit Card | S9: Economy | T9: Processing | U9: Online | V9: Priya Sinha | W9: West | X9: Pune | Y9: Maharashtra | Z9: West | AA9: 513907 | AB9: None | AC9: 4 | AD9: No | AE9: other | AF9: WH-04 | AG9: Delhivery | AH9: 45267 | AI9: 45274 | AJ9: 45282 | AK9: vishal_chaudhary@yahoo_co_in | AL9: 9541458685
A10: ORD-2023008 | B10: Arjun Nair | C10: Wholesale | D10: Fastrack Watch | E10: Fastrack | F10: Fashion | G10: Accessories | H10: 2430 | I10: =Sales_Transactions_Raw[[#This Row],[Unit_Price]]*Sales_Transactions_Raw[[#This Row],[Quantity]] -> 9720 | J10: 4 | K10: 5 | L10: 486 | M10: 9234 | N10: 12 | O10: 1108.08 | P10: 0 | Q10: 10342.08 | R10: Emi | S10: Same Day | T10: Pending | U10: Partner | V10: Aman Bhatia | W10: West | X10: Surat | Y10: Gujarat | Z10: West | AA10: 773687 | AB10: Newuser | AC10: 4 | AD10: No | AE10: other | AF10: WH-02 | AG10: Ekart | AH10: 45128 | AI10: 45131 | AJ10: 45139 | AK10: arjun_nair@gmail_com | AL10: 6994680443
A11: ORD-2023181 | B11: Jyoti Narayan | C11: Corporate | D11: Canon Eos 200D | E11: Canon | F11: Electronics | G11: Cameras | H11: 54230 | I11: =Sales_Transactions_Raw[[#This Row],[Unit_Price]]*Sales_Transactions_Raw[[#This Row],[Quantity]] -> 162690 | J11: 3 | K11: 5 | L11: 8134.5 | M11: 154555.5 | N11: 18 | O11: 27819.99 | P11: 0 | Q11: 182375.49 | R11: Cash On Delivery | S11: Express | T11: Pending | U11: Phone | V11: Priya Sinha | W11: West | X11: Chandigarh | Y11: Punjab | Z11: North | AA11: 369250 | AB11: None | AC11: 3 | AD11: No | AE11: other | AF11: WH-05 | AG11: Ekart | AH11: 44952 | AI11: 44953 | AJ11: 44958 | AK11: jyoti_narayan@yahoo_com | AL11: 7708317278
A12: ORD-2023170 | B12: Prakash Dubey | C12: Retail | D12: Hp Laserjet 1020 | E12: Hp | F12: Electronics | G12: Printers | H12: 11660 | I12: =Sales_Transactions_Raw[[#This Row],[Unit_Price]]*Sales_Transactions_Raw[[#This Row],[Quantity]] -> 81620 | J12: 7 | K12: 0 | L12: 0 | M12: 81620 | N12: 18 | O12: 14691.6 | P12: 0 | Q12: 96311.6 | R12: Debit Card | S12: Express | T12: Delivered | U12: Online | V12: Raj Kumar | W12: North | X12: Kochi | Y12: Kerala | Z12: South | AA12: 523161 | AB12: None | AC12: 3 | AD12: No | AE12: other | AF12: WH-11 | AG12: Delhivery | AH12: 45219 | AI12: 45221 | AJ12: 45227 | AK12: dubey_prakash@rediffmail_com | AL12: 8967054668
A13: ORD-2023045 | B13: Roshni Modi | C13: Corporate | D13: Boat Rockerz 450 | E13: Boat | F13: Electronics | G13: Audio | H13: 1590 | I13: =Sales_Transactions_Raw[[#This Row],[Unit_Price]]*Sales_Transactions_Raw[[#This Row],[Quantity]] -> 3180 | J13: 2 | K13: 0 | L13: 0 | M13: 3180 | N13: 18 | O13: 572.4 | P13: 149 | Q13: 3752.4 | R13: Credit Card | S13: Economy | T13: Delivered | U13: Online | V13: Neha Kulkarni | W13: West | X13: Nashik | Y13: Maharashtra | Z13: West | AA13: 503538 | AB13: None | AC13: 4 | AD13: Yes | AE13: Late Delivery | AF13: WH-02 | AG13: Dtdc | AH13: 45315 | AI13: 45318 | AJ13: 45323 | AK13: roshni_modi@gmail_com | AL13: 6092327193
... A17: ORD-2023048 | B17: Ramachandran Pillai | C17: Retail | D17: Nilkamal Chair | E17: Nilkamal | F17: Furniture | G17: Seating | H17: 4470 | I17: =Sales_Transactions_Raw[[#This Row],[Unit_Price]]*Sales_Transactions_Raw[[#This Row],[Quantity]] -> 17880 | J17: 4 | K17: 10 | L17: 1788 | M17: 16092 | N17: 5 | O17: 804.6 | P17: 0 | Q17: 16896.6 | R17: Wallet | S17: Overnight | T17: Returned | U17: Store | V17: Neha Kulkarni | W17: West | X17: Kozhikode | Y17: Kerala | Z17: South | AA17: 392603 | AB17: None | AC17: 4 | AD17: Yes | AE17: Changed Mind | AF17: WH-08 | AG17: Dtdc | AH17: 44960 | AI17: 44962 | AJ17: 44968 | AK17: ramachandran_pillai@gmail_com | AL17: 6994717464
A18: ORD-2023087 | B18: Neha Saxena | C18: Retail | D18: Lavie Handbag | E18: Lavie | F18: Fashion | G18: Bags | H18: 2880 | I18: =Sales_Transactions_Raw[[#This Row],[Unit_Price]]*Sales_Transactions_Raw[[#This Row],[Quantity]] -> 5760 | J18: 2 | K18: 20 | L18: 1152 | M18: 4608 | N18: 12 | O18: 552.96 | P18: 0 | Q18: 5160.96 | R18: Emi | S18: Economy | T18: Delivered | U18: Mobile App | V18: Pooja Nair | W18: South | X18: Vijayawada | Y18: Andhra Pradesh | Z18: South | AB18: None | AC18: 5 | AD18: No | AE18: other | AF18: WH-07 | AG18: Delhivery | AH18: 45430 | AI18: 45431 | AJ18: 45440 | AK18: neha_saxena@gmail_com | AL18: 6876038597
A19: ORD-2023046 | B19: Roshni Modi | C19: Retail | D19: Macbook Air M2 | E19: Apple | F19: Electronics | G19: Laptops | H19: 121050 | I19: =Sales_Transactions_Raw[[#This Row],[Unit_Price]]*Sales_Transactions_Raw[[#This Row],[Quantity]] -> 121050 | J19: 1 | K19: 25 | L19: 30262.5 | M19: 90787.5 | N19: 18 | O19: 16341.75 | P19: 0 | Q19: 107129.25 | R19: Cash On Delivery | S19: Express | T19: Delivered | U19: Phone | V19: Vinay Joshi | W19: Central | X19: Jamshedpur | Y19: Jharkhand | Z19: East | AA19: 605952 | AB19: Flat500 | AC19: 5 | AD19: No | AE19: other | AF19: WH-07 | AG19: Bluedart | AH19: 45084 | AI19: 45088 | AJ19: 45094 | AK19: roshni_modi@gmail_com | AL19: 6404499727
A20: ORD-2023184 | B20: Ravi Shankar | C20: Retail | D20: Levi'S 511 Jeans | E20: Levi'S | F20: Fashion | G20: Clothing | H20: 3170 | I20: =Sales_Transactions_Raw[[#This Row],[Unit_Price]]*Sales_Transactions_Raw[[#This Row],[Quantity]] -> 19020 | J20: 6 | K20: 10 | L20: 1902 | M20: 17118 | N20: 12 | O20: 2054.16 | P20: 0 | Q20: 19172.16 | R20: Emi | S20: Express | T20: Delivered | U20: Phone | V20: Priya Sinha | W20: West | X20: Nagpur | Y20: Maharashtra | Z20: West | AA20: 503050 | AB20: None | AC20: 5 | AD20: No | AE20: other | AF20: WH-04 | AG20: Dtdc | AH20: 45441 | AI20: 45357 | AJ20: 45571 | AK20: ravi_shankar@gmail_com | AL20: 8657809134
A21: ORD-2023065 | B21: Pooja Agarwal | C21: Retail | D21: Boat Rockerz 450 | E21: Boat | F21: Electronics | G21: Audio | H21: 1430 | I21: =Sales_Transactions_Raw[[#This Row],[Unit_Price]]*Sales_Transactions_Raw[[#This Row],[Quantity]] -> 4290 | J21: 3 | K21: 10 | L21: 429 | M21: 3861 | N21: 18 | O21: 694.98 | P21: 149 | Q21: 4555.98 | R21: Credit Card | S21: Economy | T21: Delivered | U21: Mobile App | V21: Ankit Sharma | W21: North | X21: Gurugram | Y21: Haryana | Z21: North | AA21: 410097 | AB21: None | AC21: 4 | AD21: No | AE21: other | AF21: WH-04 | AG21: Dtdc | AH21: 45318 | AI21: 45323 | AJ21: 45328 | AK21: pagarwal@gmail_com | AL21: 7367136959
A22: ORD-2023182 | B22: Ajay Pandey | C22: Corporate | D22: Godrej Interio Desk | E22: Godrej | F22: Furniture | G22: Desks | H22: 17450 | I22: =Sales_Transactions_Raw[[#This Row],[Unit_Price]]*Sales_Transactions_Raw[[#This Row],[Quantity]] -> 52350 | J22: 3 | K22: 5 | L22: 2617.5 | M22: 49732.5 | N22: 5 | O22: 2486.62 | P22: 0 | Q22: 52219.12 | R22: Emi | S22: Express | T22: Shipped | U22: Online | V22: Pooja Nair | W22: South | X22: Bengaluru | Y22: Karnataka | Z22: South | AA22: 499519 | AB22: Newuser | AC22: 3 | AD22: No | AE22: other | AF22: WH-04 | AG22: Bluedart | AH22: 45067 | AI22: 45073 | AJ22: 45076 | AK22: pandey_ajay@outlook_com | AL22: 6474517123
A23: ORD-2023164 | B23: Preeti Deshpande | C23: Retail | D23: Godrej Interio Desk | E23: Godrej | F23: Furniture | G23: Desks | H23: 17740 | I23: =Sales_Transactions_Raw[[#This Row],[Unit_Price]]*Sales_Transactions_Raw[[#This Row],[Quantity]] -> 35480 | J23: 2 | K23: 0 | L23: 0 | M23: 35480 | N23: 5 | O23: 1774 | P23: 0 | Q23: 37254 | R23: Upi | S23: Economy | T23: Returned | U23: Online | V23: Pooja Nair | W23: South | X23: Jodhpur | Y23: Rajasthan | Z23: North | AA23: 586806 | AB23: Festive20 | AC23: 4 | AD23: Yes | AE23: Late Delivery | AF23: WH-11 | AG23: Dtdc | AH23: 45080 | AI23: 45263 | AJ23: 45006 | AK23: deshpande_preeti@gmail_com | AL23: 6617964053
A24: ORD-2023034 | B24: Rajeev Pawar | C24: Retail | D24: Nikon D3500 | E24: Nikon | F24: Electronics | G24: Cameras | H24: 37060 | I24: =Sales_Transactions_Raw[[#This Row],[Unit_Price]]*Sales_Transactions_Raw[[#This Row],[Quantity]] -> 37060 | J24: 1 | K24: 5 | L24: 1853 | M24: 35207 | N24: 18 | O24: 6337.26 | P24: 0 | Q24: 41544.26 | R24: Cash On Delivery | S24: Standard | T24: Delivered | U24: Mobile App | V24: Ritu Singh | W24: Central | X24: Ghaziabad | Y24: Uttar Pradesh | Z24: North | AA24: 590293 | AB24: Summer15 | AC24: 5 | AD24: No | AE24: other | AF24: WH-01 | AG24: Delhivery | AH24: 45137 | AI24: 45138 | AJ24: 45148 | AK24: rpawar@hotmail_com | AL24: 9950240268
A25: ORD-2023125 | B25: Jayesh Vora | C25: Wholesale | D25: Kurl-On King Bed | E25: Kurl-On | F25: Furniture | G25: Beds | H25: 51710 | I25: =Sales_Transactions_Raw[[#This Row],[Unit_Price]]*Sales_Transactions_Raw[[#This Row],[Quantity]] -> 51710 | J25: 1 | K25: 10 | L25: 5171 | M25: 46539 | N25: 5 | O25: 2326.95 | P25: 0 | Q25: 48865.95 | R25: Emi | S25: Same Day | T25: Shipped | U25: Phone | V25: Karim Sheikh | W25: North | X25: Noida | Y25: Uttar Pradesh | Z25: North | AA25: 693398 | AB25: None | AC25: 4 | AD25: No | AE25: other | AF25: WH-09 | AG25: Dtdc | AH25: 45381 | AI25: 45382 | AJ25: 45385 | AK25: vora_jayesh@rediffmail_com | AL25: 7673657661
A26: ORD-2023129 | B26: Varsha Shinde | C26: Retail | D26: Centuary Mattress | E26: Centuary | F26: Furniture | G26: Beds | H26: 14310 | I26: =Sales_Transactions_Raw[[#This Row],[Unit_Price]]*Sales_Transactions_Raw[[#This Row],[Quantity]] -> 42930 | J26: 3 | K26: 10 | L26: 4293 | M26: 38637 | N26: 5 | O26: 1931.85 | P26: 0 | Q26: 40568.85 | R26: Credit Card | S26: Same Day | T26: Delivered | U26: Partner | V26: Sneha Reddy | W26: South | X26: Jabalpur | Y26: Madhya Pradesh | Z26: Central | AA26: 436776 | AB26: Diwali25 | AC26: 4 | AD26: No | AE26: other | AF26: WH-10 | AG26: Dtdc | AH26: 44979 | AI26: 44982 | AJ26: 44988 | AK26: shinde_varsha@yahoo_co_in | AL26: 9094024455
A27: ORD-2023064 | B27: Sanjay Mishra | C27: Corporate | D27: Tata Tea Premium 1Kg | E27: Tata | F27: Grocery | G27: Beverages | H27: 450 | I27: =Sales_Transactions_Raw[[#This Row],[Unit_Price]]*Sales_Transactions_Raw[[#This Row],[Quantity]] -> 900 | J27: 2 | K27: 0 | L27: 0 | M27: 900 | N27: 5 | O27: 45 | P27: 49 | Q27: 945 | R27: Credit Card | S27: Same Day | T27: Delivered | U27: Partner | V27: Anjali Mehta | W27: South | X27: Gaya | Y27: Bihar | Z27: East | AA27: 781238 | AB27: None | AC27: 4 | AD27: No | AE27: other | AF27: WH-02 | AG27: Bluedart | AH27: 45010 | AI27: 45013 | AJ27: 45022 | AK27: sanjaym@gmail_com | AL27: 8451076226
A28: ORD-2023069 | B28: Hussain Ali | C28: Corporate | D28: Adidas Ultraboost 22 | E28: Adidas | F28: Fashion | G28: Footwear | H28: 14050 | I28: =Sales_Transactions_Raw[[#This Row],[Unit_Price]]*Sales_Transactions_Raw[[#This Row],[Quantity]] -> 42150 | J28: 3 | K28: 5 | L28: 2107.5 | M28: 40042.5 | N28: 12 | O28: 4805.1 | P28: 0 | Q28: 44847.6 | R28: Upi | S28: Express | T28: Delivered | U28: Mobile App | V28: Arjun Das | W28: East | X28: Vadodara | Y28: Gujarat | Z28: West | AA28: 730149 | AB28: Summer15 | AC28: 4 | AD28: No | AE28: other | AF28: WH-09 | AG28: Delhivery | AH28: 45017 | AI28: 45021 | AJ28: 45024 | AK28: hussaina@yahoo_co_in | AL28: 6432921277
A29: ORD-2023036 | B29: Kavita Reddy | C29: Retail | D29: Voltas 1.5T Ac | E29: Voltas | F29: Appliances | G29: Air Conditioners | H29: 40760 | I29: =Sales_Transactions_Raw[[#This Row],[Unit_Price]]*Sales_Transactions_Raw[[#This Row],[Quantity]] -> 122280 | J29: 3 | K29: 15 | L29: 18342 | M29: 103938 | N29: 5 | O29: 5196.9 | P29: 0 | Q29: 109134.9 | R29: Wallet | S29: Overnight | T29: Delivered | U29: Store | V29: Raj Kumar | W29: North | X29: Mangaluru | Y29: Karnataka | Z29: South | AA29: 798458 | AB29: Diwali25 | AC29: 4 | AD29: No | AE29: other | AF29: WH-10 | AG29: Amazon Logistics | AH29: 45019 | AI29: 45024 | AJ29: 45034 | AK29: kavita_reddy@gmail_com | AL29: 7037788925
A30: ORD-2023117 | B30: Jyoti Narayan | C30: Retail | D30: Pepperfry Coffee Table | E30: Pepperfry | F30: Furniture | G30: Tables | H30: 12560 | I30: =Sales_Transactions_Raw[[#This Row],[Unit_Price]]*Sales_Transactions_Raw[[#This Row],[Quantity]] -> 25120 | J30: 2 | K30: 15 | L30: 3768 | M30: 21352 | N30: 5 | O30: 1067.6 | P30: 0 | Q30: 22419.6 | R30: Wallet | S30: Overnight | T30: Shipped | U30: Online | V30: Pooja Nair | W30: South | X30: Vadodara | Y30: Gujarat | Z30: West | AA30: 750256 | AB30: None | AC30: 4 | AD30: No | AE30: other | AF30: WH-12 | AG30: Ekart | AH30: 45328 | AI30: 45330 | AJ30: 45333 | AK30: jyoti_narayan@yahoo_com | AL30: 8214188805
... A68: ORD-2023133 | B68: Rekha Menon | C68: Corporate | D68: Pepperfry Coffee Table | E68: Pepperfry | F68: Furniture | G68: Tables | H68: 11550 | I68: =Sales_Transactions_Raw[[#This Row],[Unit_Price]]*Sales_Transactions_Raw[[#This Row],[Quantity]] -> 23100 | J68: 2 | K68: 5 | L68: 1155 | M68: 21945 | N68: 5 | O68: 1097.25 | P68: 0 | Q68: 23042.25 | R68: Upi | S68: Overnight | T68: Delivered | U68: Online | V68: Sneha Reddy | W68: South | X68: Durgapur | Y68: West Bengal | Z68: East | AA68: 285285 | AB68: Summer15 | AC68: 4 | AD68: No | AE68: other | AF68: WH-04 | AG68: Delhivery | AH68: 45116 | AI68: 45119 | AJ68: 45127 | AK68: menon_rekha@yahoo_co_in | AL68: 9686879374
A69: ORD-2023241 | B69: Kruti Bhatt | C69: Retail | D69: Sony Wh-1000Xm5 | E69: Sony | F69: Electronics | G69: Audio | H69: 30240 | I69: =Sales_Transactions_Raw[[#This Row],[Unit_Price]]*Sales_Transactions_Raw[[#This Row],[Quantity]] -> 90720 | J69: 3 | K69: 20 | L69: 18144 | M69: 72576 | N69: 18 | O69: 13063.68 | P69: 0 | Q69: 85639.68 | R69: Wallet | S69: Standard | T69: Delivered | U69: Partner | V69: Priya Sinha | W69: West | X69: Ranchi | Y69: Jharkhand | Z69: East | AB69: None | AC69: 4 | AD69: No | AE69: other | AF69: WH-05 | AG69: Bluedart | AH69: 45191 | AI69: 45194 | AJ69: 45197 | AK69: kruti_bhatt@gmail_com | AL69: 61485 64679
A70: ORD-2023246 | B70: Parvati Devi | C70: Wholesale | D70: Lenovo Thinkpad E14 | E70: Lenovo | F70: Electronics | G70: Laptops | H70: 60120 | I70: =Sales_Transactions_Raw[[#This Row],[Unit_Price]]*Sales_Transactions_Raw[[#This Row],[Quantity]] -> 120240 | J70: 2 | K70: 10 | L70: 12024 | M70: 108216 | N70: 18 | O70: 19478.88 | P70: 0 | Q70: 127694.88 | R70: Net Banking | S70: Express | T70: Delivered | U70: Phone | V70: Priya Sinha | W70: West | X70: Jodhpur | Y70: Rajasthan | Z70: North | AA70: 607636 | AB70: None | AC70: 4 | AD70: No | AE70: other | AF70: WH-06 | AG70: Bluedart | AH70: 45234 | AI70: 45240 | AJ70: 45249 | AK70: devi_parvati@gmail_com | AL70: 9902330307
A71: ORD-2023135 | B71: Aarav Sharma | C71: Corporate | D71: Classmate Notebook | E71: Classmate | F71: Stationery | G71: Books | H71: 130 | I71: =Sales_Transactions_Raw[[#This Row],[Unit_Price]]*Sales_Transactions_Raw[[#This Row],[Quantity]] -> 390 | J71: 3 | K71: 20 | L71: 78 | M71: 312 | N71: 5 | O71: 15.6 | P71: 79 | Q71: 327.6 | R71: Upi | S71: Economy | T71: Shipped | U71: Partner | V71: Neha Kulkarni | W71: West | X71: Gurugram | Y71: Haryana | Z71: North | AA71: 223356 | AB71: Save10 | AC71: 5 | AD71: Yes | AE71: other | AF71: WH-05 | AG71: Dtdc | AH71: 44955 | AI71: 44959 | AJ71: 44961 | AK71: aarav_sharma@gmail_com | AL71: 7446657437
A72: ORD-2023136 | B72: Lalitha Devi | C72: Retail | D72: Parker Pen Set | E72: Parker | F72: Stationery | G72: Writing | H72: 890 | I72: =Sales_Transactions_Raw[[#This Row],[Unit_Price]]*Sales_Transactions_Raw[[#This Row],[Quantity]] -> 6230 | J72: 7 | K72: 15 | L72: 934.5 | M72: 5295.5 | N72: 5 | O72: 264.77 | P72: 0 | Q72: 5560.27 | R72: Emi | S72: Same Day | T72: Shipped | U72: Store | V72: Neha Kulkarni | W72: West | X72: Jamshedpur | Y72: Jharkhand | Z72: East | AA72: 432003 | AB72: Save10 | AC72: 4 | AD72: Yes | AE72: other | AF72: WH-06 | AG72: Delhivery | AH72: 45119 | AI72: 45121 | AJ72: 45131 | AK72: devi_lalitha@gmail_com | AL72: 738758428
A73: ORD-2023101 | B73: Kunal Oberoi | C73: Corporate | D73: Realme Gt 5 | E73: Realme | F73: Electronics | G73: Mobile Phones | H73: 27470 | I73: =Sales_Transactions_Raw[[#This Row],[Unit_Price]]*Sales_Transactions_Raw[[#This Row],[Quantity]] -> 164820 | J73: 6 | K73: 0 | L73: 0 | M73: 164820 | N73: 18 | O73: 29667.6 | P73: 0 | Q73: 194487.6 | R73: Wallet | S73: Express | T73: Delivered | U73: Store | V73: Ankit Sharma | W73: North | X73: Ranchi | Y73: Jharkhand | Z73: East | AA73: 124761 | AB73: Flat500 | AC73: 3 | AD73: Yes | AE73: other | AF73: WH-04 | AG73: Delhivery | AH73: 44999 | AI73: 45003 | AJ73: 45008 | AK73: kunalo@gmail_com | AL73: 8525007432
A74: ORD-2023064 | B74: Manoj Tomar | C74: Wholesale | D74: Classmate Notebook | E74: Classmate | F74: Stationery | G74: Books | H74: 110 | I74: =Sales_Transactions_Raw[[#This Row],[Unit_Price]]*Sales_Transactions_Raw[[#This Row],[Quantity]] -> 220 | J74: 2 | K74: 0 | L74: 0 | M74: 220 | N74: 5 | O74: 11 | P74: 99 | Q74: 231 | R74: Cash On Delivery | S74: Overnight | T74: Delivered | U74: Partner | V74: Neha Kulkarni | W74: West | X74: Madurai | Y74: Tamil Nadu | Z74: South | AA74: 231415 | AB74: Diwali25 | AC74: 3 | AD74: No | AE74: other | AF74: WH-07 | AG74: Delhivery | AH74: 45059 | AI74: 45060 | AJ74: 45068 | AK74: manojt@yahoo_com | AL74: 9033230982
A75: ORD-2023252 | B75: Ravi Shankar | C75: Wholesale | D75: Jbl Flip 6 | E75: Jbl | F75: Electronics | G75: Audio | H75: 9630 | I75: =Sales_Transactions_Raw[[#This Row],[Unit_Price]]*Sales_Transactions_Raw[[#This Row],[Quantity]] -> 38520 | J75: 4 | K75: 10 | L75: 3852 | M75: 34668 | N75: 18 | O75: 6240.24 | P75: 0 | Q75: 40908.24 | R75: Wallet | S75: Standard | T75: Delivered | U75: Partner | V75: Pooja Nair | W75: South | X75: Vadodara | Y75: Gujarat | Z75: West | AA75: 352390 | AB75: None | AC75: 4 | AD75: No | AE75: other | AF75: WH-05 | AG75: Delhivery | AH75: 44936 | AI75: 44939 | AJ75: 44947 | AK75: shankar_ravi@gmail_com | AL75: 86420 87375
A76: ORD-2023084 | B76: Archana Srivastava | C76: Retail | D76: Voltas 1.5T Ac | E76: Voltas | F76: Appliances | G76: Air Conditioners | H76: 35240 | I76: =Sales_Transactions_Raw[[#This Row],[Unit_Price]]*Sales_Transactions_Raw[[#This Row],[Quantity]] -> 176200 | J76: 5 | K76: 20 | L76: 35240 | M76: 140960 | N76: 5 | O76: 7048 | P76: 0 | Q76: 148008 | R76: Debit Card | S76: Same Day | T76: Shipped | U76: Mobile App | V76: Arjun Das | W76: East | X76: Surat | Y76: Gujarat | Z76: West | AA76: 616546 | AB76: None | AC76: 5 | AD76: No | AE76: other | AF76: WH-02 | AG76: Amazon Logistics | AH76: 45363 | AI76: 45369 | AJ76: 45372 | AK76: archana_srivastava@gmail_com | AL76: 6676212021
A77: ORD-2023242 | B77: Saurabh Kulkarni | C77: Retail | D77: Iphone 15 Pro | E77: Apple | F77: Electronics | G77: Mobile Phones | H77: 87670 | I77: =Sales_Transactions_Raw[[#This Row],[Unit_Price]]*Sales_Transactions_Raw[[#This Row],[Quantity]] -> 350680 | J77: 4 | K77: 10 | L77: 35068 | M77: 315612 | N77: 18 | O77: 56810.16 | P77: 0 | Q77: 372422.16 | R77: Credit Card | S77: Economy | T77: Shipped | U77: Store | V77: Vinay Joshi | W77: Central | X77: Rajkot | Y77: Gujarat | Z77: West | AA77: 631534 | AB77: None | AC77: 3 | AD77: No | AE77: other | AF77: WH-01 | AG77: Delhivery | AH77: 45464 | AI77: 45471 | AJ77: 45476 | AK77: saurabh_kulkarni@gmail_com | AL77: 7877217535
A78: ORD-2023218 | B78: Venkatesan Rajan | C78: Wholesale | D78: Iphone 15 Pro | E78: Apple | F78: Electronics | G78: Mobile Phones | H78: 96480 | I78: =Sales_Transactions_Raw[[#This Row],[Unit_Price]]*Sales_Transactions_Raw[[#This Row],[Quantity]] -> 385920 | J78: 4 | K78: 5 | L78: 19296 | M78: 366624 | N78: 18 | O78: 65992.32 | P78: 0 | Q78: 432616.32 | R78: Debit Card | S78: Economy | T78: Delivered | U78: Mobile App | V78: Ritu Singh | W78: Central | X78: Gurugram | Y78: Haryana | Z78: North | AA78: 727414 | AB78: None | AC78: 4 | AD78: No | AE78: other | AF78: WH-08 | AG78: Bluedart | AH78: 45238 | AI78: 45243 | AJ78: 45253 | AK78: venkatesanr@gmail_com | AL78: 6488510272
A79: ORD-2023206 | B79: Farhan Khan | C79: Corporate | D79: Levi'S 511 Jeans | E79: Levi'S | F79: Fashion | G79: Clothing | H79: 3200 | I79: =Sales_Transactions_Raw[[#This Row],[Unit_Price]]*Sales_Transactions_Raw[[#This Row],[Quantity]] -> 6400 | J79: 2 | K79: 20 | L79: 1280 | M79: 5120 | N79: 12 | O79: 614.4 | P79: 0 | Q79: 5734.4 | R79: Cash On Delivery | S79: Express | T79: Delivered | U79: Store | V79: Deepa Menon | W79: South | X79: Mumbai | Y79: Maharashtra | Z79: West | AA79: 638371 | AB79: Festive20 | AC79: 3 | AD79: No | AE79: other | AF79: WH-11 | AG79: Bluedart | AH79: 44976 | AI79: 44981 | AJ79: 44989 | AK79: farhank@gmail_com | AL79: 7472269848
A80: ORD-2023168 | B80: Meenakshi Sundaram | C80: Corporate | D80: Puma Softride | E80: Puma | F80: Fashion | G80: Footwear | H80: 5250 | I80: =Sales_Transactions_Raw[[#This Row],[Unit_Price]]*Sales_Transactions_Raw[[#This Row],[Quantity]] -> 31500 | J80: 6 | K80: 10 | L80: 3150 | M80: 28350 | N80: 12 | O80: 3402 | P80: 0 | Q80: 31752 | R80: Debit Card | S80: Standard | T80: Delivered | U80: Online | V80: Ankit Sharma | W80: North | X80: Cuttack | Y80: Odisha | Z80: East | AA80: 373551 | AB80: Flat500 | AC80: 1 | AD80: No | AE80: other | AF80: WH-08 | AG80: Ekart | AH80: 45354 | AI80: 45360 | AJ80: 45370 | AK80: msundaram@gmail_com | AL80: 8057198386
A81: ORD-2023259 | B81: Thiruvengadam Natarajan | C81: VIP | D81: Pepperfry Coffee Table | E81: Pepperfry | F81: Furniture | G81: Tables | H81: 12350 | I81: =Sales_Transactions_Raw[[#This Row],[Unit_Price]]*Sales_Transactions_Raw[[#This Row],[Quantity]] -> 12350 | J81: 1 | K81: 0 | L81: 0 | M81: 12350 | N81: 5 | O81: 617.5 | P81: 0 | Q81: 12967.5 | R81: Cash On Delivery | S81: Standard | T81: Delivered | U81: Phone | V81: Ritu Singh | W81: Central | X81: Salem | Y81: Tamil Nadu | Z81: South | AA81: 417836 | AB81: Save10 | AC81: 3 | AD81: No | AE81: other | AF81: WH-10 | AG81: Dtdc | AH81: 45128 | AI81: 45135 | AJ81: 45140 | AK81: thiruvengadamnoutlook_com | AL81: 7909479851
... A85: ORD-2023146 | B85: Manoj Tomar | C85: VIP | D85: Parker Pen Set | E85: Parker | F85: Stationery | G85: Writing | H85: 900 | I85: =Sales_Transactions_Raw[[#This Row],[Unit_Price]]*Sales_Transactions_Raw[[#This Row],[Quantity]] -> 3600 | J85: 4 | K85: 5 | L85: 180 | M85: 3420 | N85: 5 | O85: 171 | P85: 99 | Q85: 3591 | R85: Net Banking | S85: Overnight | T85: Processing | U85: Online | V85: Pooja Nair | W85: South | X85: Indore | Y85: Madhya Pradesh | Z85: Central | AA85: 526060 | AB85: Summer15 | AC85: 4 | AD85: No | AE85: other | AF85: WH-01 | AG85: Ekart | AH85: 45373 | AI85: 45376 | AJ85: 45383 | AK85: manoj_tomar@yahoo_com | AL85: 7809969308
A86: ORD-2023277 | B86: Paramjit Brar | C86: Wholesale | D86: Lg 43-Inch 4K Tv | E86: Lg | F86: Electronics | G86: Televisions | H86: 41050 | I86: =Sales_Transactions_Raw[[#This Row],[Unit_Price]]*Sales_Transactions_Raw[[#This Row],[Quantity]] -> 82100 | J86: 2 | K86: 0 | L86: 0 | M86: 82100 | N86: 18 | O86: 14778 | P86: 0 | Q86: 96878 | R86: Credit Card | S86: Same Day | T86: Delivered | U86: Mobile App | V86: Priya Sinha | W86: West | X86: Kochi | Y86: Kerala | Z86: South | AB86: Flat500 | AC86: 4 | AD86: No | AE86: other | AF86: WH-03 | AG86: Bluedart | AH86: 45110 | AI86: 45115 | AJ86: 45119 | AK86: paramjit_brargmail_com | AL86: 6184498926
A87: ORD-2023216 | B87: Kannappan Ponnusamy | C87: Wholesale | D87: Hp Laserjet 1020 | E87: Hp | F87: Electronics | G87: Printers | H87: 12820 | I87: =Sales_Transactions_Raw[[#This Row],[Unit_Price]]*Sales_Transactions_Raw[[#This Row],[Quantity]] -> 64100 | J87: 5 | K87: 5 | L87: 3205 | M87: 60895 | N87: 18 | O87: 10961.1 | P87: 0 | Q87: 71856.1 | R87: Credit Card | S87: Economy | T87: Delivered | U87: Phone | V87: Priya Sinha | W87: West | X87: Jaipur | Y87: Rajasthan | Z87: North | AA87: 720949 | AB87: None | AC87: 4 | AD87: No | AE87: other | AF87: WH-03 | AG87: Dtdc | AH87: 45118 | AI87: 45115 | AJ87: 45119 | AK87: kannappanp@gmail_com | AL87: 9092024286
A88: ORD-2023128 | B88: Venugopal Krishnan | C88: Corporate | D88: Kurl-On King Bed | E88: Kurl-On | F88: Furniture | G88: Beds | H88: 52380 | I88: =Sales_Transactions_Raw[[#This Row],[Unit_Price]]*Sales_Transactions_Raw[[#This Row],[Quantity]] -> 52380 | J88: 1 | K88: 20 | L88: 10476 | M88: 41904 | N88: 5 | O88: 2095.2 | P88: 0 | Q88: 43999.2 | R88: Net Banking | S88: Express | T88: Delivered | U88: Partner | V88: Karim Sheikh | W88: North | X88: Coimbatore | Y88: Tamil Nadu | Z88: South | AA88: 353808 | AB88: Festive20 | AC88: 4 | AD88: No | AE88: other | AF88: WH-02 | AG88: Delhivery | AH88: 44997 | AI88: 44999 | AJ88: 45007 | AK88: venugopal_krishnan@gmail_com | AL88: 6980686508
A89: ORD-2023152 | B89: Ajay Pandey | C89: Corporate | D89: Iphone 15 Pro | E89: Apple | F89: Electronics | G89: Mobile Phones | H89: 92220 | I89: =Sales_Transactions_Raw[[#This Row],[Unit_Price]]*Sales_Transactions_Raw[[#This Row],[Quantity]] -> 92220 | J89: 1 | K89: 10 | L89: 9222 | M89: 82998 | N89: 18 | O89: 14939.64 | P89: 0 | Q89: 97937.64 | R89: Upi | S89: Standard | T89: Delivered | U89: Store | V89: Aman Bhatia | W89: West | X89: Rajkot | Y89: Gujarat | Z89: West | AA89: 464878 | AB89: None | AC89: 4 | AD89: No | AE89: other | AF89: WH-10 | AG89: Ekart | AH89: 44934 | AI89: 44939 | AJ89: 44949 | AK89: ajay_pandey@outlook_com | AL89: 7887258874
A90: ORD-2023187 | B90: Janaki Ramanathan | C90: Wholesale | D90: Iphone 15 Pro | E90: Apple | F90: Electronics | G90: Mobile Phones | H90: 88140 | I90: =Sales_Transactions_Raw[[#This Row],[Unit_Price]]*Sales_Transactions_Raw[[#This Row],[Quantity]] -> 88140 | J90: 1 | K90: 10 | L90: 8814 | M90: 79326 | N90: 18 | O90: 14278.68 | P90: 0 | Q90: 93604.68 | R90: Net Banking | S90: Overnight | T90: Shipped | U90: Partner | V90: Vinay Joshi | W90: Central | X90: Gurugram | Y90: Haryana | Z90: North | AA90: 204546 | AB90: Newuser | AC90: 4 | AD90: No | AE90: other | AF90: WH-12 | AG90: Ekart | AH90: 45075 | AI90: 45079 | AJ90: 45087 | AK90: janakir@gmail_com | AL90: 9430988392
A91: ORD-2023178 | B91: Girish More | C91: VIP | D91: Hp Laserjet 1020 | E91: Hp | F91: Electronics | G91: Printers | H91: 12310 | I91: =Sales_Transactions_Raw[[#This Row],[Unit_Price]]*Sales_Transactions_Raw[[#This Row],[Quantity]] -> 12310 | J91: 1 | K91: 0 | L91: 0 | M91: 12310 | N91: 18 | O91: 2215.8 | P91: 0 | Q91: 14525.8 | R91: Upi | S91: Same Day | T91: Delivered | U91: Online | V91: Ankit Sharma | W91: North | X91: Jodhpur | Y91: Rajasthan | Z91: North | AA91: 468606 | AB91: None | AC91: 5 | AD91: No | AE91: other | AF91: WH-03 | AG91: Bluedart | AH91: 45126 | AI91: 45130 | AJ91: 45138 | AK91: more_girish@gmail_com | AL91: 6577907141
A92: ORD-2023236 | B92: Harish Malhotra | C92: Retail | D92: Boat Rockerz 450 | E92: Boat | F92: Electronics | G92: Audio | H92: 1440 | I92: =Sales_Transactions_Raw[[#This Row],[Unit_Price]]*Sales_Transactions_Raw[[#This Row],[Quantity]] -> 1440 | J92: 1 | K92: 0 | L92: 0 | M92: 1440 | N92: 18 | O92: 259.2 | P92: 79 | Q92: 1699.2 | R92: Upi | S92: Express | T92: Pending | U92: Online | V92: Pooja Nair | W92: South | X92: Indore | Y92: Madhya Pradesh | Z92: Central | AA92: 653378 | AB92: Festive20 | AC92: 5 | AD92: No | AE92: other | AF92: WH-12 | AG92: Delhivery | AH92: 45121 | AI92: 45125 | AJ92: 45130 | AK92: harish_malhotra@gmail_com | AL92: 6957947284
A93: ORD-2023188 | B93: Chandra Sekar | C93: VIP | D93: Lenovo Thinkpad E14 | E93: Lenovo | F93: Electronics | G93: Laptops | H93: 62260 | I93: =Sales_Transactions_Raw[[#This Row],[Unit_Price]]*Sales_Transactions_Raw[[#This Row],[Quantity]] -> 62260 | J93: 1 | K93: 5 | L93: 3113 | M93: 59147 | N93: 18 | O93: 10646.46 | P93: 0 | Q93: 69793.46 | R93: Net Banking | S93: Express | T93: Delivered | U93: Phone | V93: Arjun Das | W93: East | X93: Chennai | Y93: Tamil Nadu | Z93: South | AA93: 172953 | AB93: Diwali25 | AC93: 3 | AD93: No | AE93: other | AF93: WH-05 | AG93: Bluedart | AH93: 45192 | AI93: 45194 | AJ93: 45204 | AK93: chandra_sekar@gmail_com | AL93: 6866322702
A94: ORD-2023207 | B94: Aarav Sharma | C94: Retail | D94: Samsung 253L Fridge | E94: Samsung | F94: Appliances | G94: Refrigerators | H94: 24930 | I94: =Sales_Transactions_Raw[[#This Row],[Unit_Price]]*Sales_Transactions_Raw[[#This Row],[Quantity]] -> 24930 | J94: 1 | K94: 0 | L94: 0 | M94: 24930 | N94: 5 | O94: 1246.5 | P94: 0 | Q94: 26176.5 | R94: Cash On Delivery | S94: Express | T94: Pending | U94: Partner | V94: Arjun Das | W94: East | X94: Bengaluru | Y94: Karnataka | Z94: South | AA94: 490806 | AB94: None | AC94: 4 | AD94: No | AE94: other | AF94: WH-09 | AG94: India Post | AH94: 45383 | AI94: 45536 | AJ94: 45310 | AK94: aarav_sharma@gmail_com | AL94: 6947225699
A95: ORD-2023098 | B95: Kiran Rao | C95: Retail | D95: Camlin Art Kit | E95: Camlin | F95: Stationery | G95: Art Supplies | H95: 560 | I95: =Sales_Transactions_Raw[[#This Row],[Unit_Price]]*Sales_Transactions_Raw[[#This Row],[Quantity]] -> 1120 | J95: 2 | K95: 20 | L95: 224 | M95: 896 | N95: 5 | O95: 44.8 | P95: 149 | Q95: 940.8 | R95: Credit Card | S95: Economy | T95: Delivered | U95: Partner | V95: Pooja Nair | W95: South | X95: Udaipur | Y95: Rajasthan | Z95: North | AA95: 474033 | AB95: Festive20 | AC95: 4 | AD95: No | AE95: other | AF95: WH-04 | AG95: Ekart | AH95: 45184 | AI95: 45190 | AJ95: 45193 | AK95: krao@gmail_com | AL95: 7282005577
A96: ORD-2023199 | B96: Usha Chopra | C96: Wholesale | D96: Sony Bravia 55-Inch | E96: Sony | F96: Electronics | G96: Televisions | H96: 72790 | I96: =Sales_Transactions_Raw[[#This Row],[Unit_Price]]*Sales_Transactions_Raw[[#This Row],[Quantity]] -> 145580 | J96: 2 | K96: 20 | L96: 29116 | M96: 116464 | N96: 18 | O96: 20963.52 | P96: 0 | Q96: 137427.52 | R96: Net Banking | S96: Same Day | T96: Returned | U96: Online | V96: Anjali Mehta | W96: South | X96: Hubballi | Y96: Karnataka | Z96: South | AA96: 306912 | AB96: None | AC96: 5 | AD96: Yes | AE96: Changed Mind | AF96: WH-01 | AG96: India Post | AH96: 44927 | AI96: 44932 | AJ96: 44936 | AK96: chopra_usha@yahoo_co_in | AL96: 7266341638
A97: ORD-2023197 | B97: Tarun Bansal | C97: Retail | D97: Hp Laserjet 1020 | E97: Hp | F97: Electronics | G97: Printers | H97: 12490 | I97: =Sales_Transactions_Raw[[#This Row],[Unit_Price]]*Sales_Transactions_Raw[[#This Row],[Quantity]] -> 12490 | J97: 1 | K97: 5 | L97: 624.5 | M97: 11865.5 | N97: 18 | O97: 2135.79 | P97: 0 | Q97: 14001.29 | R97: Wallet | S97: Economy | T97: Delivered | U97: Mobile App | V97: Aman Bhatia | W97: West | X97: Ghaziabad | Y97: Uttar Pradesh | Z97: North | AA97: 154236 | AB97: None | AC97: 4 | AD97: No | AE97: other | AF97: WH-09 | AG97: Dtdc | AH97: 45375 | AI97: 45381 | AJ97: 45383 | AK97: tarun_bansal@outlook_com | AL97: 8234601367
A98: ORD-2023172 | B98: Sushma Yadav | C98: Retail | D98: Voltas 1.5T Ac | E98: Voltas | F98: Appliances | G98: Air Conditioners | H98: 35980 | I98: =Sales_Transactions_Raw[[#This Row],[Unit_Price]]*Sales_Transactions_Raw[[#This Row],[Quantity]] -> 71960 | J98: 2 | K98: 0 | L98: 0 | M98: 71960 | N98: 5 | O98: 3598 | P98: 0 | Q98: 75558 | R98: Wallet | S98: Express | T98: Delivered | U98: Online | V98: Vinay Joshi | W98: Central | X98: Nashik | Y98: Maharashtra | Z98: West | AA98: 568753 | AB98: Save10 | AC98: 4 | AD98: No | AE98: other | AF98: WH-09 | AG98: Ekart | AH98: 45150 | AI98: 45151 | AJ98: 45156 | AK98: sushma_yadav@gmail_com | AL98: 8500528127
... A158: ORD-2023327 | B158: Mitesh Gandhi | C158: Wholesale | D158: Kurl-On King Bed | E158: Kurl-On | F158: Furniture | G158: Beds | H158: 57740 | I158: =Sales_Transactions_Raw[[#This Row],[Unit_Price]]*Sales_Transactions_Raw[[#This Row],[Quantity]] -> 346440 | J158: 6 | K158: 25 | L158: 86610 | M158: 259830 | N158: 5 | O158: 12991.5 | P158: 0 | Q158: 272821.5 | R158: Upi | S158: Express | T158: Delivered | U158: Phone | V158: Arjun Das | W158: East | X158: Faridabad | Y158: Haryana | Z158: North | AA158: 726736 | AB158: Save10 | AC158: 4 | AD158: No | AE158: other | AF158: WH-02 | AG158: Delhivery | AH158: 45312 | AI158: 45319 | AJ158: 45326 | AK158: gandhi_mitesh@gmail_com | AL158: 8375047930
A159: ORD-2023343 | B159: Seema Kapoor | C159: Retail | D159: Sony Wh-1000Xm5 | E159: Sony | F159: Electronics | G159: Audio | H159: 27600 | I159: =Sales_Transactions_Raw[[#This Row],[Unit_Price]]*Sales_Transactions_Raw[[#This Row],[Quantity]] -> 193200 | J159: 7 | K159: 5 | L159: 9660 | M159: 183540 | N159: 18 | O159: 33037.2 | P159: 0 | Q159: 216577.2 | R159: Emi | S159: Standard | T159: Shipped | U159: Mobile App | V159: Anjali Mehta | W159: South | X159: Surat | Y159: Gujarat | Z159: West | AB159: None | AC159: 5 | AD159: No | AE159: other | AF159: WH-07 | AG159: Ekart | AH159: 45472 | AI159: 45477 | AJ159: 45483 | AK159: seema_kapoor@gmail_com | AL159: 704687506
A160: ORD-2023243 | B160: Naveen Bajaj | C160: Retail | D160: Nikon D3500 | E160: Nikon | F160: Electronics | G160: Cameras | H160: 33520 | I160: =Sales_Transactions_Raw[[#This Row],[Unit_Price]]*Sales_Transactions_Raw[[#This Row],[Quantity]] -> 100560 | J160: 3 | K160: 0 | L160: 0 | M160: 100560 | N160: 18 | O160: 18100.8 | P160: 0 | Q160: 118660.8 | R160: Net Banking | S160: Standard | T160: Shipped | U160: Phone | V160: Karim Sheikh | W160: North | X160: Noida | Y160: Uttar Pradesh | Z160: North | AA160: 216198 | AB160: None | AC160: 4 | AD160: Yes | AE160: Defective | AF160: WH-08 | AG160: Dtdc | AH160: 45171 | AI160: 45174 | AJ160: 45176 | AK160: naveenb@gmail_com__ | AL160: 7049611080
A161: ORD-2023311 | B161: Uma Shankar | C161: Retail | D161: Dell Xps 15 Laptop | E161: Dell | F161: Electronics | G161: Laptops | H161: 123420 | I161: =Sales_Transactions_Raw[[#This Row],[Unit_Price]]*Sales_Transactions_Raw[[#This Row],[Quantity]] -> 123420 | J161: 1 | K161: 15 | L161: 18513 | M161: 104907 | N161: 18 | O161: 18883.26 | P161: 0 | Q161: 123790.26 | R161: Debit Card | S161: Express | T161: Delivered | U161: Online | V161: Ritu Singh | W161: Central | X161: Cuttack | Y161: Odisha | Z161: East | AA161: 600107 | AB161: Save10 | AC161: 4 | AD161: No | AE161: other | AF161: WH-06 | AG161: Amazon Logistics | AH161: 45125 | AI161: 45130 | AJ161: 45134 | AK161: shankar_uma@gmail_com | AL161: 8749545089
A162: ORD-2023201 | B162: Anita Bhatt | C162: Retail | D162: Adidas Ultraboost 22 | E162: Adidas | F162: Fashion | G162: Footwear | H162: 13360 | I162: =Sales_Transactions_Raw[[#This Row],[Unit_Price]]*Sales_Transactions_Raw[[#This Row],[Quantity]] -> 40080 | J162: 3 | K162: 5 | L162: 1336 | M162: 25384 | N162: 12 | O162: 3046.08 | P162: 0 | Q162: 28430.08 | R162: Wallet | S162: Same Day | T162: Processing | U162: Phone | V162: Karim Sheikh | W162: North | X162: Nagpur | Y162: Maharashtra | Z162: West | AA162: 226360 | AB162: Flat500 | AC162: 3 | AD162: No | AE162: other | AF162: WH-04 | AG162: Bluedart | AH162: 45125 | AI162: 45130 | AJ162: 45157 | AK162: anitab@outlook_com | AL162: 7950033423
A163: ORD-2023256 | B163: Muthukrishnan Arunachalam | C163: Wholesale | D163: Samsung 65-Inch Qled | E163: Samsung | F163: Electronics | G163: Televisions | H163: 89390 | I163: =Sales_Transactions_Raw[[#This Row],[Unit_Price]]*Sales_Transactions_Raw[[#This Row],[Quantity]] -> 625730 | J163: 7 | K163: 0 | L163: 0 | M163: 625730 | N163: 18 | O163: 112631.4 | P163: 0 | Q163: 738361.4 | R163: Emi | S163: Same Day | T163: Delivered | U163: Mobile App | V163: Ritu Singh | W163: Central | X163: Howrah | Y163: West Bengal | Z163: East | AA163: 616774 | AB163: None | AC163: 3 | AD163: No | AE163: other | AF163: WH-08 | AG163: Bluedart | AH163: 45371 | AI163: 45377 | AJ163: 45380 | AK163: marunachalam@gmail_com | AL163: 6304289731
A164: ORD-2023328 | B164: Rohit Singh | C164: Retail | D164: Jbl Flip 6 | E164: Jbl | F164: Electronics | G164: Audio | H164: 10620 | I164: =Sales_Transactions_Raw[[#This Row],[Unit_Price]]*Sales_Transactions_Raw[[#This Row],[Quantity]] -> 21240 | J164: 2 | K164: 10 | L164: 2124 | M164: 19116 | N164: 18 | O164: 3440.88 | P164: 0 | Q164: 22556.88 | R164: Upi | S164: Same Day | T164: Returned | U164: Partner | V164: Suraj Verma | W164: East | X164: Jodhpur | Y164: Rajasthan | Z164: North | AA164: 234349 | AB164: Festive20 | AC164: 4 | AD164: Yes | AE164: Defective | AF164: WH-09 | AG164: Delhivery | AH164: 45389 | AI164: 45396 | AJ164: 45401 | AK164: rohit_singh@outlook_com | AL164: 66776 65754
A165: ORD-2023353 | B165: Parvati Devi | C165: Retail | D165: Hp Laserjet 1020 | E165: Hp | F165: Electronics | G165: Printers | H165: 12100 | I165: =Sales_Transactions_Raw[[#This Row],[Unit_Price]]*Sales_Transactions_Raw[[#This Row],[Quantity]] -> 12100 | J165: 1 | K165: 15 | L165: 1815 | M165: 10285 | N165: 18 | O165: 1851.3 | P165: 0 | Q165: 12136.3 | R165: Net Banking | S165: Economy | T165: Processing | U165: Partner | V165: Aman Bhatia | W165: West | X165: Chandigarh | Y165: Punjab | Z165: North | AA165: 549508 | AB165: None | AC165: 4 | AD165: No | AE165: other | AF165: WH-07 | AG165: Ekart | AH165: 45068 | AI165: 45075 | AJ165: 45144 | AK165: parvatid@gmail_com | AL165: 6987751536
A166: ORD-2023314 | B166: Amit Kumar | C166: Retail | D166: Wildcraft Backpack | E166: Wildcraft | F166: Fashion | G166: Bags | H166: 1960 | I166: =Sales_Transactions_Raw[[#This Row],[Unit_Price]]*Sales_Transactions_Raw[[#This Row],[Quantity]] -> 1960 | J166: 1 | K166: 10 | L166: 196 | M166: 1764 | N166: 12 | O166: 211.68 | P166: 79 | Q166: 1975.68 | R166: Upi | S166: Overnight | T166: Delivered | U166: Phone | V166: Priya Sinha | W166: West | X166: Nagpur | Y166: Maharashtra | Z166: West | AA166: 326510 | AB166: None | AC166: 5 | AD166: No | AE166: other | AF166: WH-04 | AG166: Bluedart | AH166: 45084 | AI166: 45087 | AJ166: 45144 | AK166: amit_kumar@hotmail_com | AL166: 9164334817
A167: ORD-2023335 | B167: Kunal Oberoi | C167: Corporate | D167: Samsung 65-Inch Qled | E167: Samsung | F167: Electronics | G167: Televisions | H167: 91590 | I167: =Sales_Transactions_Raw[[#This Row],[Unit_Price]]*Sales_Transactions_Raw[[#This Row],[Quantity]] -> 366360 | J167: 4 | K167: 0 | L167: 0 | M167: 366360 | N167: 18 | O167: 65944.8 | P167: 0 | Q167: 432304.8 | R167: Credit Card | S167: Economy | T167: Delivered | U167: Partner | V167: Ankit Sharma | W167: North | X167: Patna | Y167: Bihar | Z167: East | AA167: 179987 | AB167: Flat500 | AC167: 4 | AD167: No | AE167: other | AF167: WH-12 | AG167: Amazon Logistics | AH167: 45244 | AI167: 45249 | AJ167: 45254 | AK167: koberoi@gmail_com | AL167: 6546926329
A168: ORD-2023271 | B168: Chandni Gupta | C168: Corporate | D168: Titan Raga | E168: Titan | F168: Fashion | G168: Accessories | H168: 8870 | I168: =Sales_Transactions_Raw[[#This Row],[Unit_Price]]*Sales_Transactions_Raw[[#This Row],[Quantity]] -> 26610 | J168: 3 | K168: 0 | L168: 0 | M168: 44350 | N168: 12 | O168: 5322 | P168: 0 | Q168: 49672 | R168: Credit Card | S168: Economy | T168: Delivered | U168: Online | V168: Arjun Das | W168: East | X168: Faridabad | Y168: Haryana | Z168: North | AA168: 396526 | AB168: Festive20 | AC168: 4 | AD168: No | AE168: other | AF168: WH-06 | AG168: Delhivery | AH168: 45005 | AI168: 45012 | AJ168: 45015 | AK168: chandni_gupta@gmail_com | AL168: 6257771183
A169: ORD-2023303 | B169: Divya Krishnan | C169: Corporate | D169: Nike Air Max 270 | E169: Nike | F169: Fashion | G169: Footwear | H169: 10210 | I169: =Sales_Transactions_Raw[[#This Row],[Unit_Price]]*Sales_Transactions_Raw[[#This Row],[Quantity]] -> 20420 | J169: 2 | K169: 0 | L169: 0 | M169: 20420 | N169: 12 | O169: 2450.4 | P169: 0 | Q169: 22870.4 | R169: Wallet | S169: Express | T169: Processing | U169: Store | V169: Anjali Mehta | W169: South | X169: Vadodara | Y169: Gujarat | Z169: West | AA169: 340788 | AB169: Diwali25 | AC169: 5 | AD169: No | AE169: other | AF169: WH-05 | AG169: Dtdc | AH169: 45462 | AI169: 45012 | AJ169: 45015 | AK169: divya_krishnan@gmail_com | AL169: 8220681558
A170: ORD-2023273 | B170: Dinesh Thakur | C170: Wholesale | D170: Maggi Noodles 12-Pack | E170: Nestlé | F170: Grocery | G170: Instant Foods | H170: 180 | I170: =Sales_Transactions_Raw[[#This Row],[Unit_Price]]*Sales_Transactions_Raw[[#This Row],[Quantity]] -> 1440 | J170: 8 | K170: 0 | L170: 0 | M170: 1440 | N170: 5 | O170: 72 | P170: 49 | Q170: 1512 | R170: Emi | S170: Economy | T170: Shipped | U170: Store | V170: Karim Sheikh | W170: North | X170: Patna | Y170: Bihar | Z170: East | AA170: 737128 | AB170: Diwali25 | AC170: 4 | AD170: No | AE170: other | AF170: WH-08 | AG170: Ekart | AH170: 45031 | AI170: 45037 | AJ170: 45047 | AK170: dinesh_thakur@gmail_com | AL170: 9768389030
A171: ORD-2023333 | B171: Chandni Gupta | C171: Retail | D171: Oneplus 12 | E171: Oneplus | F171: Electronics | G171: Mobile Phones | H171: 67420 | I171: =Sales_Transactions_Raw[[#This Row],[Unit_Price]]*Sales_Transactions_Raw[[#This Row],[Quantity]] -> 67420 | J171: 1 | K171: 5 | L171: 3371 | M171: 64049 | N171: 18 | O171: 11528.82 | P171: 0 | Q171: 75577.82 | R171: Credit Card | S171: Express | T171: Delivered | U171: Store | V171: Ritu Singh | W171: Central | X171: Howrah | Y171: West Bengal | Z171: East | AA171: 614545 | AB171: None | AC171: 5 | AD171: No | AE171: other | AF171: WH-06 | AG171: Bluedart | AH171: 45351 | AI171: 45357 | AJ171: 45363 | AK171: chandnig@gmail_com__ | AL171: 9321298338
... A200: ORD-2023288 | B200: Varsha Shinde | C200: Retail | D200: Fastrack Watch | E200: Fastrack | F200: Fashion | G200: Accessories | H200: 2520 | I200: =Sales_Transactions_Raw[[#This Row],[Unit_Price]]*Sales_Transactions_Raw[[#This Row],[Quantity]] -> 5040 | J200: 2 | K200: 0 | L200: 0 | M200: 5040 | N200: 12 | O200: 604.8 | P200: 0 | Q200: 5644.8 | R200: Upi | S200: Economy | T200: Delivered | U200: Mobile App | V200: Deepa Menon | W200: South | X200: Vijayawada | Y200: Andhra Pradesh | Z200: South | AA200: 786185 | AB200: None | AC200: 5 | AD200: No | AE200: other | AF200: WH-12 | AG200: Bluedart | AH200: 45270 | AI200: 45271 | AJ200: 45275 | AK200: varsha_shinde@yahoo_co_in | AL200: 7179817890
A201: ORD-2023399 | B201: Manoj Tomar | C201: Corporate | D201: Van Heusen Shirt | E201: Van Heusen | F201: Fashion | G201: Clothing | H201: 1700 | I201: =Sales_Transactions_Raw[[#This Row],[Unit_Price]]*Sales_Transactions_Raw[[#This Row],[Quantity]] -> 1700 | J201: 1 | K201: 0 | L201: 0 | M201: 1700 | N201: 12 | O201: 204 | P201: 49 | Q201: 1904 | R201: Upi | S201: Overnight | T201: Delivered | U201: Partner | V201: Neha Kulkarni | W201: West | X201: Mangaluru | Y201: Karnataka | Z201: South | AB201: Diwali25 | AC201: 3 | AD201: Yes | AE201: Defective | AF201: WH-11 | AG201: Ekart | AH201: 45197 | AI201: 45200 | AJ201: 45208 | AK201: manoj_tomar@yahoo_com | AL201: 862626582
A202: ORD-2023358 | B202: Thiruvengadam Natarajan | C202: Retail | D202: Fastrack Watch | E202: Fastrack | F202: Fashion | G202: Accessories | H202: 2610 | I202: =Sales_Transactions_Raw[[#This Row],[Unit_Price]]*Sales_Transactions_Raw[[#This Row],[Quantity]] -> 7830 | J202: 3 | K202: 0 | L202: 0 | M202: 7830 | N202: 12 | O202: 939.6 | P202: 0 | Q202: 8769.6 | R202: Debit Card | S202: Same Day | T202: Shipped | U202: Store | V202: Ankit Sharma | W202: North | X202: Gurugram | Y202: Haryana | Z202: North | AA202: 550305 | AB202: None | AC202: 5 | AD202: No | AE202: other | AF202: WH-06 | AG202: Dtdc | AH202: 45318 | AI202: 45319 | AJ202: 45323 | AK202: thiruvengadam_natarajan@outlook_com | AL202: 7911791124
A203: ORD-2023369 | B203: Anand Swaminathan | C203: Corporate | D203: Durian Sofa 3-Seat | E203: Durian | F203: Furniture | G203: Sofas | H203: 45820 | I203: =Sales_Transactions_Raw[[#This Row],[Unit_Price]]*Sales_Transactions_Raw[[#This Row],[Quantity]] -> 91640 | J203: 2 | K203: 10 | L203: 9164 | M203: 82476 | N203: 5 | O203: 4123.8 | P203: 0 | Q203: 86599.8 | R203: Emi | S203: Same Day | T203: Delivered | U203: Online | V203: Vinay Joshi | W203: Central | X203: Patna | Y203: Bihar | Z203: East | AA203: 726122 | AB203: Flat500 | AC203: 4 | AD203: No | AE203: other | AF203: WH-04 | AG203: India Post | AH203: 44959 | AI203: 44960 | AJ203: 44967 | AK203: anands@gmail_com | AL203: 7312447315
A204: ORD-2023310 | B204: Eswaran Murugan | C204: Retail | D204: Amul Butter 500G | E204: Amul | F204: Grocery | G204: Dairy | H204: 280 | I204: =Sales_Transactions_Raw[[#This Row],[Unit_Price]]*Sales_Transactions_Raw[[#This Row],[Quantity]] -> 560 | J204: 2 | K204: 5 | L204: 28 | M204: 532 | N204: 5 | O204: 26.6 | P204: 49 | Q204: 558.6 | R204: Credit Card | S204: Overnight | T204: Delivered | U204: Mobile App | V204: Vinay Joshi | W204: Central | X204: Mysuru | Y204: Karnataka | Z204: South | AA204: 217920 | AB204: None | AC204: 3 | AD204: No | AE204: other | AF204: WH-12 | AG204: Dtdc | AH204: 45253 | AI204: 45258 | AJ204: 45261 | AK204: eswaran_murugan@rediffmail_com | AL204: 7625313552
A205: ORD-2023374 | B205: Nisha Jain | C205: Corporate | D205: Wildcraft Backpack | E205: Wildcraft | F205: Fashion | G205: Bags | H205: 2000 | I205: =Sales_Transactions_Raw[[#This Row],[Unit_Price]]*Sales_Transactions_Raw[[#This Row],[Quantity]] -> 2000 | J205: 1 | K205: 0 | L205: 0 | M205: 2000 | N205: 12 | O205: 240 | P205: 99 | Q205: 2240 | R205: Credit Card | S205: Economy | T205: Delivered | U205: Store | V205: Sneha Reddy | W205: South | X205: Jamshedpur | Y205: Jharkhand | Z205: East | AA205: 586664 | AB205: None | AC205: 3 | AD205: No | AE205: other | AF205: WH-11 | AG205: India Post | AH205: 45372 | AI205: 45375 | AJ205: 45382 | AK205: nisha_jain@gmail_com | AL205: 626088050
A206: ORD-2023299 | B206: Hussain Ali | C206: Corporate | D206: Lenovo Thinkpad E14 | E206: Lenovo | F206: Electronics | G206: Laptops | H206: 61350 | I206: =Sales_Transactions_Raw[[#This Row],[Unit_Price]]*Sales_Transactions_Raw[[#This Row],[Quantity]] -> 1227000 | J206: 20 | K206: 15 | L206: 184050 | M206: 1042950 | N206: 18 | O206: 187731 | P206: 0 | Q206: 1230681 | R206: Credit Card | S206: Express | T206: Delivered | U206: Mobile App | V206: Suraj Verma | W206: East | X206: Pune | Y206: Maharashtra | Z206: West | AA206: 447549 | AB206: None | AC206: 5 | AD206: No | AE206: other | AF206: WH-08 | AG206: Delhivery | AH206: 44975 | AI206: 44982 | AJ206: 44984 | AK206: hali@yahoo_co_in | AL206: 7964229712
A207: ORD-2023387 | B207: Vijay Pillai | C207: Retail | D207: Godrej 236L Fridge | E207: Godrej | F207: Appliances | G207: Refrigerators | H207: 21980 | I207: =Sales_Transactions_Raw[[#This Row],[Unit_Price]]*Sales_Transactions_Raw[[#This Row],[Quantity]] -> 21980 | J207: 1 | K207: 0 | L207: 0 | M207: 21980 | N207: 5 | O207: 1099 | P207: 0 | Q207: 23079 | R207: Net Banking | S207: Economy | T207: Shipped | U207: Store | V207: Vinay Joshi | W207: Central | X207: Asansol | Y207: West Bengal | Z207: East | AA207: 593233 | AB207: None | AC207: 4 | AD207: No | AE207: other | AF207: WH-01 | AG207: Bluedart | AH207: 45175 | AI207: 45181 | AJ207: 45186 | AK207: vpillai@gmail_com | AL207: 8812356798
A208: ORD-2023296 | B208: Usha Chopra | C208: Corporate | D208: Macbook Air M2 | E208: Apple | F208: Electronics | G208: Laptops | H208: 115050 | I208: =Sales_Transactions_Raw[[#This Row],[Unit_Price]]*Sales_Transactions_Raw[[#This Row],[Quantity]] -> 345150 | J208: 3 | K208: 0 | L208: 0 | M208: 345150 | N208: 18 | O208: 62127 | P208: 0 | Q208: 407277 | R208: Credit Card | S208: Standard | T208: Delivered | U208: Phone | V208: Raj Kumar | W208: North | X208: Asansol | Y208: West Bengal | Z208: East | AA208: 777838 | AB208: None | AC208: 4 | AD208: No | AE208: other | AF208: WH-10 | AG208: Delhivery | AH208: 45289 | AI208: 45293 | AJ208: 45298 | AK208: usha_chopra@yahoo_co_in | AL208: 9131009431
A209: ORD-2023118 | B209: Balwinder Sandhu | C209: Retail | D209: Classmate Notebook | E209: Classmate | F209: Stationery | G209: Books | H209: 110 | I209: =Sales_Transactions_Raw[[#This Row],[Unit_Price]]*Sales_Transactions_Raw[[#This Row],[Quantity]] -> 440 | J209: 4 | K209: 5 | L209: 22 | M209: 418 | N209: 5 | O209: 20.9 | P209: 149 | Q209: 438.9 | R209: Credit Card | S209: Economy | T209: Delivered | U209: Phone | V209: Karim Sheikh | W209: North | X209: Gaya | Y209: Bihar | Z209: East | AA209: 491986 | AB209: Diwali25 | AC209: 4 | AD209: Yes | AE209: other | AF209: WH-05 | AG209: Ekart | AH209: 45239 | AI209: 45246 | AJ209: 45251 | AK209: bsandhu@gmail_com | AL209: 8073710094
A210: ORD-2023406 | B210: Muthukrishnan Arunachalam | C210: Retail | D210: Nilkamal Chair | E210: Nilkamal | F210: Furniture | G210: Seating | H210: 4840 | I210: =Sales_Transactions_Raw[[#This Row],[Unit_Price]]*Sales_Transactions_Raw[[#This Row],[Quantity]] -> 4840 | J210: 1 | K210: 20 | L210: 968 | M210: 3872 | N210: 5 | O210: 193.6 | P210: 79 | Q210: 4065.6 | R210: Credit Card | S210: Express | T210: Delivered | U210: Partner | V210: Raj Kumar | W210: North | X210: Kozhikode | Y210: Kerala | Z210: South | AA210: 264279 | AB210: None | AC210: 3 | AD210: No | AE210: other | AF210: WH-03 | AG210: Dtdc | AH210: 45203 | AI210: 45209 | AJ210: 45219 | AK210: arunachalam_muthukrishnan@gmail_com | AL210: 7824556964
A211: ORD-2023351 | B211: Nagalakshmi Venkatesh | C211: Retail | D211: Samsung 65-Inch Qled | E211: Samsung | F211: Electronics | G211: Televisions | H211: 91700 | I211: =Sales_Transactions_Raw[[#This Row],[Unit_Price]]*Sales_Transactions_Raw[[#This Row],[Quantity]] -> 91700 | J211: 1 | K211: 10 | L211: 9170 | M211: 82530 | N211: 18 | O211: 14855.4 | P211: 0 | Q211: 97385.4 | R211: Upi | S211: Standard | T211: Delivered | U211: Phone | V211: Karim Sheikh | W211: North | X211: Hubballi | Y211: Karnataka | Z211: South | AA211: 448145 | AB211: Diwali25 | AC211: 4 | AD211: No | AE211: other | AF211: WH-03 | AG211: Ekart | AH211: 45222 | AI211: 45223 | AJ211: 45229 | AK211: venkatesh_nagalakshmi@yahoo_com | AL211: 6423691430
A212: ORD-2023261 | B212: Dinesh Thakur | C212: Corporate | D212: Whirlpool 7Kg Washer | E212: Whirlpool | F212: Appliances | G212: Washing Machines | H212: 31680 | I212: =Sales_Transactions_Raw[[#This Row],[Unit_Price]]*Sales_Transactions_Raw[[#This Row],[Quantity]] -> 190080 | J212: 6 | K212: 0 | L212: 0 | M212: 190080 | N212: 5 | O212: 9504 | P212: 0 | Q212: 199584 | R212: Upi | S212: Overnight | T212: Delivered | U212: Mobile App | V212: Neha Kulkarni | W212: West | X212: Gurugram | Y212: Haryana | Z212: North | AA212: 222249 | AB212: None | AC212: 3 | AD212: No | AE212: other | AF212: WH-02 | AG212: Ekart | AH212: 45399 | AI212: 45404 | AJ212: 45408 | AK212: dinesh_thakur@gmail_com | AL212: 7943985298
A213: ORD-2023400 | B213: Chandra Sekar | C213: Corporate | D213: Kurl-On King Bed | E213: Kurl-On | F213: Furniture | G213: Beds | H213: 59110 | I213: =Sales_Transactions_Raw[[#This Row],[Unit_Price]]*Sales_Transactions_Raw[[#This Row],[Quantity]] -> 177330 | J213: 3 | K213: 0 | L213: 0 | M213: 177330 | N213: 5 | O213: 8866.5 | P213: 0 | Q213: 186196.5 | R213: Emi | S213: Express | T213: Returned | U213: Mobile App | V213: Aman Bhatia | W213: West | X213: Kolkata | Y213: West Bengal | Z213: East | AA213: 239181 | AB213: None | AC213: 2 | AD213: Yes | AE213: Defective | AF213: WH-03 | AG213: Delhivery | AH213: 44981 | AI213: 45404 | AJ213: 44992 | AK213: chandra_sekar@gmail_com__ | AL213: 6918133170
... A216: ORD-2023403 | B216: Sanjay Mishra | C216: Retail | D216: Milton Water Purifier | E216: Milton | F216: Appliances | G216: Kitchen | H216: 9520 | I216: =Sales_Transactions_Raw[[#This Row],[Unit_Price]]*Sales_Transactions_Raw[[#This Row],[Quantity]] -> 38080 | J216: 4 | K216: 15 | L216: 5712 | M216: 32368 | N216: 5 | O216: 1618.4 | P216: 0 | Q216: 33986.4 | R216: Upi | S216: Economy | T216: Returned | U216: Partner | V216: Ritu Singh | W216: Central | X216: Howrah | Y216: West Bengal | Z216: East | AA216: 413979 | AB216: None | AC216: 5 | AD216: Yes | AE216: other | AF216: WH-07 | AG216: Ekart | AH216: 45123 | AI216: 45124 | AJ216: 45126 | AK216: mishra_sanjay@gmail_com | AL216: 6978559821
A217: ORD-2023362 | B217: Prakash Dubey | C217: Retail | D217: Peter England Suit | E217: Peter England | F217: Fashion | G217: Clothing | H217: 9120 | I217: =Sales_Transactions_Raw[[#This Row],[Unit_Price]]*Sales_Transactions_Raw[[#This Row],[Quantity]] -> 63840 | J217: 7 | K217: 20 | L217: 12768 | M217: 51072 | N217: 12 | O217: 6128.64 | P217: 0 | Q217: 57200.64 | R217: Emi | S217: Standard | T217: Cancelled | U217: Online | V217: Deepa Menon | W217: South | X217: Gaya | Y217: Bihar | Z217: East | AB217: Diwali25 | AC217: 3 | AD217: No | AE217: other | AF217: WH-01 | AG217: Delhivery | AH217: 45246 | AI217: 45250 | AJ217: 45252 | AK217: pdubey@rediffmail_com | AL217: 9371990516
A218: ORD-2023313 | B218: Parvati Devi | C218: Retail | D218: Kurl-On King Bed | E218: Kurl-On | F218: Furniture | G218: Beds | H218: 54380 | I218: =Sales_Transactions_Raw[[#This Row],[Unit_Price]]*Sales_Transactions_Raw[[#This Row],[Quantity]] -> 217520 | J218: 4 | K218: 5 | L218: 10876 | M218: 206644 | N218: 5 | O218: 10332.2 | P218: 0 | Q218: 216976.2 | R218: Net Banking | S218: Standard | T218: Delivered | U218: Partner | V218: Anjali Mehta | W218: South | X218: Indore | Y218: Madhya Pradesh | Z218: Central | AA218: 325861 | AB218: Diwali25 | AC218: 3 | AD218: No | AE218: other | AF218: WH-12 | AG218: Ekart | AH218: 45420 | AI218: 45421 | AJ218: 45429 | AK218: parvati_devi@gmail_com | AL218: 8900301027
A219: ORD-2023416 | B219: Venkatesan Rajan | C219: Retail | D219: Epson L3250 | E219: Epson | F219: Electronics | G219: Printers | H219: 14860 | I219: =Sales_Transactions_Raw[[#This Row],[Unit_Price]]*Sales_Transactions_Raw[[#This Row],[Quantity]] -> 44580 | J219: 3 | K219: 20 | L219: 8916 | M219: 35664 | N219: 18 | O219: 6419.52 | P219: 0 | Q219: 42083.52 | R219: Cash On Delivery | S219: Economy | T219: Shipped | U219: Mobile App | V219: Suraj Verma | W219: East | X219: Jamshedpur | Y219: Jharkhand | Z219: East | AA219: 562026 | AB219: Festive20 | AC219: 4 | AD219: No | AE219: other | AF219: WH-11 | AG219: Bluedart | AH219: 45466 | AI219: 45469 | AJ219: 45476 | AK219: vrajan@gmail_com | AL219: 7037710704
A220: ORD-2023307 | B220: Sunita Verma | C220: Corporate | D220: Nilkamal Chair | E220: Nilkamal | F220: Furniture | G220: Seating | H220: 4740 | I220: =Sales_Transactions_Raw[[#This Row],[Unit_Price]]*Sales_Transactions_Raw[[#This Row],[Quantity]] -> 9480 | J220: 2 | K220: 5 | L220: 474 | M220: 9006 | N220: 5 | O220: 450.3 | P220: 0 | Q220: 9456.3 | R220: Emi | S220: Standard | T220: Delivered | U220: Online | V220: Arjun Das | W220: East | X220: Jabalpur | Y220: Madhya Pradesh | Z220: Central | AA220: 431803 | AB220: None | AC220: 3 | AD220: No | AE220: other | AF220: WH-06 | AG220: Ekart | AH220: 45195 | AI220: 45202 | AJ220: 45207 | AK220: verma_sunita@gmail_com | AL220: 9426732044
A221: ORD-2023332 | B221: Roshni Modi | C221: Wholesale | D221: Samsung Galaxy S24 | E221: Samsung | F221: Electronics | G221: Mobile Phones | H221: 71610 | I221: =Sales_Transactions_Raw[[#This Row],[Unit_Price]]*Sales_Transactions_Raw[[#This Row],[Quantity]] -> 429660 | J221: 6 | K221: 0 | L221: 0 | M221: 429660 | N221: 18 | O221: 77338.8 | P221: 0 | Q221: 506998.8 | R221: Upi | S221: Overnight | T221: Returned | U221: Partner | V221: Anjali Mehta | W221: South | X221: Kochi | Y221: Kerala | Z221: South | AA221: 476719 | AB221: Diwali25 | AC221: 5 | AD221: Yes | AE221: other | AF221: WH-08 | AG221: Delhivery | AH221: 45404 | AI221: 45405 | AJ221: 45412 | AK221: roshni_modi@gmail_com | AL221: 72903 10287
A222: ORD-2023394 | B222: Foram Trivedi | C222: VIP | D222: Dell Xps 15 Laptop | E222: Dell | F222: Electronics | G222: Laptops | H222: 121700 | I222: =Sales_Transactions_Raw[[#This Row],[Unit_Price]]*Sales_Transactions_Raw[[#This Row],[Quantity]] -> 608500 | J222: 5 | K222: 5 | L222: 30425 | M222: 578075 | N222: 18 | O222: 104053.5 | P222: 0 | Q222: 682128.5 | R222: Net Banking | S222: Same Day | T222: Shipped | U222: Partner | V222: Sneha Reddy | W222: South | X222: Jamshedpur | Y222: Jharkhand | Z222: East | AA222: 659924 | AB222: Save10 | AC222: 4 | AD222: No | AE222: other | AF222: WH-06 | AG222: Delhivery | AH222: 45216 | AI222: 45218 | AJ222: 45412 | AK222: ftrivedi@gmail_com | AL222: 9953690261
A223: ORD-2023305 | B223: Sangita Ghosh | C223: VIP | D223: Maggi Noodles 12-Pack | E223: Nestlé | F223: Grocery | G223: Instant Foods | H223: 190 | I223: =Sales_Transactions_Raw[[#This Row],[Unit_Price]]*Sales_Transactions_Raw[[#This Row],[Quantity]] -> 380 | J223: 2 | K223: 5 | L223: 19 | M223: 361 | N223: 5 | O223: 18.05 | P223: 49 | Q223: 379.05 | R223: Cash On Delivery | S223: Standard | T223: Delivered | U223: Mobile App | V223: Suraj Verma | W223: East | X223: Salem | Y223: Tamil Nadu | Z223: South | AA223: 602685 | AB223: None | AC223: 4 | AD223: No | AE223: other | AF223: WH-03 | AG223: Amazon Logistics | AH223: 45393 | AI223: 45396 | AJ223: 45399 | AK223: ghosh_sangita@gmail_com | AL223: 6929445511
A224: ORD-2023228 | B224: Ramachandran Pillai | C224: Retail | D224: Samsung 65-Inch Qled | E224: Samsung | F224: Electronics | G224: Televisions | H224: 92790 | I224: =Sales_Transactions_Raw[[#This Row],[Unit_Price]]*Sales_Transactions_Raw[[#This Row],[Quantity]] -> 649530 | J224: 7 | K224: 5 | L224: 32476.5 | M224: 617053.5 | N224: 18 | O224: 111069.63 | P224: 0 | Q224: 728123.13 | R224: Emi | S224: Same Day | T224: Shipped | U224: Online | V224: Priya Sinha | W224: West | X224: Delhi | Y224: Delhi | Z224: North | AA224: 467688 | AB224: Diwali25 | AC224: 5 | AD224: No | AE224: other | AF224: WH-09 | AG224: Amazon Logistics | AH224: 45602 | AI224: 45461 | AJ224: 45471 | AK224: rpillai@gmail_com | AL224: 8764722981
A225: ORD-2023321 | B225: Saurabh Kulkarni | C225: Corporate | D225: Tata Tea Premium 1Kg | E225: Tata | F225: Grocery | G225: Beverages | H225: 480 | I225: =Sales_Transactions_Raw[[#This Row],[Unit_Price]]*Sales_Transactions_Raw[[#This Row],[Quantity]] -> 480 | J225: 1 | K225: 5 | L225: 24 | M225: 456 | N225: 5 | O225: 22.8 | P225: 99 | Q225: 478.8 | R225: Credit Card | S225: Same Day | T225: Delivered | U225: Mobile App | V225: Priya Sinha | W225: West | X225: Kanpur | Y225: Uttar Pradesh | Z225: North | AA225: 235767 | AB225: None | AC225: 3 | AD225: No | AE225: other | AF225: WH-07 | AG225: Bluedart | AH225: 44969 | AI225: 44976 | AJ225: 44981 | AK225: saurabhk@gmail_com | AL225: 81388 20908
A226: ORD-2023411 | B226: Nagalakshmi Venkatesh | C226: Wholesale | D226: Macbook Air M2 | E226: Apple | F226: Electronics | G226: Laptops | H226: 115030 | I226: =Sales_Transactions_Raw[[#This Row],[Unit_Price]]*Sales_Transactions_Raw[[#This Row],[Quantity]] -> 230060 | J226: 2 | K226: 0 | L226: 0 | M226: 230060 | N226: 18 | O226: 41410.8 | P226: 0 | Q226: 271470.8 | R226: Cash On Delivery | S226: Standard | T226: Shipped | U226: Mobile App | V226: Ritu Singh | W226: south | X226: Madurai | Y226: Tamil Nadu | Z226: South | AA226: 328678 | AB226: Save10 | AC226: 3 | AD226: No | AE226: other | AF226: WH-01 | AG226: Bluedart | AH226: 45007 | AI226: 45013 | AJ226: 45018 | AK226: nagalakshmi_venkatesh@yahoo_com | AL226: 6329633472
A227: ORD-2023322 | B227: Indira Gandhi | C227: Retail | D227: Lavie Handbag | E227: Lavie | F227: Fashion | G227: Bags | H227: 2710 | I227: =Sales_Transactions_Raw[[#This Row],[Unit_Price]]*Sales_Transactions_Raw[[#This Row],[Quantity]] -> 2710 | J227: 1 | K227: 0 | L227: 0 | M227: 2710 | N227: 12 | O227: 325.2 | P227: 99 | Q227: 3035.2 | R227: Net Banking | S227: Economy | T227: Shipped | U227: Partner | V227: Pooja Nair | W227: South | X227: Udaipur | Y227: Rajasthan | Z227: North | AA227: 448892 | AB227: Diwali25 | AC227: 4 | AD227: No | AE227: other | AF227: WH-06 | AG227: Bluedart | AH227: 45284 | AI227: 45288 | AJ227: 45298 | AK227: indira_gandhi@gmail_com | AL227: 8361275156
A228: ORD-2023334 | B228: Hina Shah | C228: Corporate | D228: Logitech Mx Master 3 | E228: Logitech | F228: Electronics | G228: Accessories | H228: 8720 | I228: =Sales_Transactions_Raw[[#This Row],[Unit_Price]]*Sales_Transactions_Raw[[#This Row],[Quantity]] -> 43600 | J228: 5 | K228: 5 | L228: 2180 | M228: 41420 | N228: 18 | O228: 7455.6 | P228: 0 | Q228: 48875.6 | R228: Debit Card | S228: Overnight | T228: Shipped | U228: Store | V228: Neha Kulkarni | W228: West | X228: Nashik | Y228: Maharashtra | Z228: West | AA228: 131002 | AB228: None | AC228: 4 | AD228: Yes | AE228: other | AF228: WH-02 | AG228: Dtdc | AH228: 45424 | AI228: 45430 | AJ228: 45435 | AK228: hina_shah@yahoo_com | AL228: 8558108358
A229: ORD-2023237 | B229: Sanjay Mishra | C229: Retail | D229: Epson L3250 | E229: Epson | F229: Electronics | G229: Printers | H229: 16800 | I229: =Sales_Transactions_Raw[[#This Row],[Unit_Price]]*Sales_Transactions_Raw[[#This Row],[Quantity]] -> 67200 | J229: 4 | K229: 5 | L229: 3360 | M229: 63840 | N229: 18 | O229: 11491.2 | P229: 0 | Q229: 75331.2 | R229: Wallet | S229: Same Day | T229: Delivered | U229: Online | V229: Anjali Mehta | W229: South | X229: Hubballi | Y229: Karnataka | Z229: South | AA229: 669105 | AB229: Festive20 | AC229: 4 | AD229: No | AE229: other | AF229: WH-07 | AG229: Delhivery | AH229: 45162 | AI229: 45168 | AJ229: 45435 | AK229: mishra_sanjay@gmail_com | AL229: 7963945680
A230: ORD-2023423 | B230: Jayalakshmi Kumar | C230: Retail | D230: Parker Pen Set | E230: Parker | F230: Stationery | G230: Writing | H230: 830 | I230: =Sales_Transactions_Raw[[#This Row],[Unit_Price]]*Sales_Transactions_Raw[[#This Row],[Quantity]] -> 830 | J230: 1 | K230: 10 | L230: 83 | M230: 747 | N230: 5 | O230: 37.35 | P230: 99 | Q230: 784.35 | R230: Wallet | S230: Standard | T230: Delivered | U230: Online | V230: Karim Sheikh | W230: North | X230: Noida | Y230: Uttar Pradesh | Z230: North | AA230: 616459 | AB230: None | AC230: 4 | AD230: No | AE230: other | AF230: WH-12 | AG230: India Post | AH230: 45156 | AI230: 45161 | AJ230: 45163 | AK230: jayalakshmi_kumar@gmail_com | AL230: 7307464520
A231: ORD-2023408 | B231: Nisha Jain | C231: VIP | D231: Daikin 1.5T Inverter | E231: Daikin | F231: Appliances | G231: Air Conditioners | H231: 45540 | I231: =Sales_Transactions_Raw[[#This Row],[Unit_Price]]*Sales_Transactions_Raw[[#This Row],[Quantity]] -> 45540 | J231: 1 | K231: 25 | L231: 11385 | M231: 34155 | N231: 5 | O231: 1707.75 | P231: 0 | Q231: 35862.75 | R231: Net Banking | S231: Economy | T231: Delivered | U231: Store | V231: Ritu Singh | W231: Central | X231: Ghaziabad | Y231: Uttar Pradesh | Z231: North | AB231: None | AC231: 5 | AD231: No | AE231: other | AF231: WH-07 | AG231: Delhivery | AH231: 44940 | AI231: 44942 | AJ231: 44952 | AK231: nisha_jain@gmail_com | AL231: 8859592248
A232: ORD-2023231 | B232: Jyoti Narayan | C232: Retail | D232: Classmate Notebook | E232: Classmate | F232: Stationery | G232: Books | H232: 120 | I232: =Sales_Transactions_Raw[[#This Row],[Unit_Price]]*Sales_Transactions_Raw[[#This Row],[Quantity]] -> 120 | J232: 1 | K232: 0 | L232: 0 | M232: 120 | N232: 5 | O232: 6 | P232: 99 | Q232: 126 | R232: Debit Card | S232: Same Day | T232: Shipped | U232: Online | V232: Suraj Verma | W232: East | X232: Chandigarh | Y232: Punjab | Z232: North | AA232: 606404 | AB232: Flat500 | AC232: 2 | AD232: No | AE232: other | AF232: WH-01 | AG232: Ekart | AH232: 45023 | AI232: 45028 | AJ232: 45037 | AK232: jyoti_narayan@yahoo_com | AL232: 7831921342
...

Sheet Sheet2
F3: =Sales_Transactions_Raw!H2*Sales_Transactions_Raw!J2 -> 81690 | H3: =Sales_Transactions_Raw!M2*Sales_Transactions_Raw!N2 -> 1396899
F4: =F3*5% -> 4084.5 | I4: =H3+Sales_Transactions_Raw!M2 -> 1474504.5
F5: =F3-F4 -> 77605.5
G7: =(Sales_Transactions_Raw!H2*Sales_Transactions_Raw!J2)-Sales_Transactions_Raw!K2 -> 81685

Sheet Sheet1
B2: ETL | C2: extract | D2: raw data(we can get data from different sources)
C3: transform | D3: data cleaning | E3: power query
C4: load | D4: ready to analize,ready visualize
H5: =Sales_Transactions_Raw!H2*Sales_Transactions_Raw!J2*Sales_Transactions_Raw!K2 -> 408450
H11: saurabh.kulkarni@@gmail.com
